velha_test_files/nand2_flat.vhd
library ieee;
use ieee.std_logic_1164.all;
entity nand2_flat is
	generic (
		tpd : integer := 1000000
	);
	port (
		a: in std_logic;
		b: in std_logic;
		y: out std_logic
	);
end nand2_flat;

architecture rtl of nand2_flat is
begin
	y <= not  (a And b) after 1000000 fs;
end rtl;

velha_test_files/01_nand2.vhd
-- Rung 1: smoke test.
-- Exercises: context clause, entity with generic + port clause, port modes,
-- architecture body, one concurrent signal assignment, physical literal,
-- 'after' waveform element, optional closing labels.
library ieee;
use ieee.std_logic_1164.all;

entity nand2 is
    generic (
        tpd : time := 1 ns
    );
    port (
        a, b : in std_logic;
        y : out std_logic
    );
end entity nand2;

architecture rtl of nand2 is
begin
    y <= not (a and b) after tpd;
end architecture rtl;

-- Add other types for std_logic

-- Show driver contention on unresolved type
library ieee;
use ieee.std_logic_1164.all;
entity d_contention is
    generic (
        tpd : time := 1 ns
    );
    port (
        a, b : in std_logic;
        y : out integer
    );
end entity d_contention;

architecture rtl of d_contention is
begin
    y <= 67;
    y <= 68;
end architecture rtl;

velha_test_files/tb_nand2_equiv.vhd
library ieee;
use ieee.std_logic_1164.all;
use ieee.numeric_std.all;
entity tb_nand2_equiv is
end entity tb_nand2_equiv;

architecture behavioral of tb_nand2_equiv is
    signal a : std_logic;
    signal b : std_logic;
    signal y_rtl : std_logic;
    signal y_rtl_flat : std_logic;

begin
    U_RTL: entity work.nand2(rtl)
        port map (
        a => a,
        b => b,
        y => y_rtl
        );

    U_RTL_FLAT: entity work.nand2_flat(rtl)
        port map (
        a => a,
        b => b,
        y => y_rtl_flat
        );

    STIMULUS_PROC: process
    begin
        -- Stimulus Vector 0
        a <= '0';
        b <= '0';
        wait for 10 ns;
        assert y_rtl_flat = y_rtl
            report "Equivalence Mismatch on entity 'nand2', port 'y' (arch 'rtl') for vector 0" severity error;

        -- Stimulus Vector 1
        a <= '1';
        b <= '0';
        wait for 10 ns;
        assert y_rtl_flat = y_rtl
            report "Equivalence Mismatch on entity 'nand2', port 'y' (arch 'rtl') for vector 1" severity error;

        -- Stimulus Vector 2
        a <= '0';
        b <= '1';
        wait for 10 ns;
        assert y_rtl_flat = y_rtl
            report "Equivalence Mismatch on entity 'nand2', port 'y' (arch 'rtl') for vector 2" severity error;

        -- Stimulus Vector 3
        a <= '1';
        b <= '1';
        wait for 10 ns;
        assert y_rtl_flat = y_rtl
            report "Equivalence Mismatch on entity 'nand2', port 'y' (arch 'rtl') for vector 3" severity error;

        wait;
    end process;
end architecture;
-- ========================================================

wave.vcd
$date
  Tue Oct 06 11:25:45 2026
$end
$version
  GHDL v0
$end
$timescale
  1 fs
$end
$scope module standard $end
$upscope $end
$scope module std_logic_1164 $end
$upscope $end
$scope module numeric_std $end
$upscope $end
$scope module tb_nand2_equiv $end
$var reg 1 ! a $end
$var reg 1 " b $end
$var reg 1 # y_rtl $end
$var reg 1 $ y_rtl_flat $end
$scope module u_rtl $end
$var reg 1 % a $end
$var reg 1 & b $end
$var reg 1 ' y $end
$upscope $end
$scope module u_rtl_flat $end
$var reg 1 ( a $end
$var reg 1 ) b $end
$var reg 1 * y $end
$upscope $end
$upscope $end
$enddefinitions $end
#0
0!
0"
U#
U$
0%
0&
U'
0(
0)
U*
#1000000
1#
1$
1'
1*
#10000000
1!
1%
1(
#11000000
1'
1*
#20000000
0!
1"
0%
1&
0(
1)
#21000000
1'
1*
#30000000
1!
1%
1(
#31000000
0#
0$
0'
0*
